Metadata-Version: 1.1
Name: sortseq-tools
Version: 0.0.20
Summary: Tools for analysis of Sort-Seq experiments.
Home-page: UNKNOWN
Author: Bill Ireland
Author-email: irelandb99999@gmail.com
License: UNKNOWN
Download-URL: https://github.com/jbkinney/sortseq/tarball/0.1
Platform: Linux (and maybe also Mac OS X).
